.pylintrc
ACKNOWLEDGEMENTS
AUTHORS
LICENSE
MANIFEST.in
MANIFEST.test_data.in
README
appveyor.yml
dependencies.ini
requirements.txt
run_tests.py
setup.cfg
setup.py
test_dependencies.ini
test_requirements.txt
tox.ini
winevt-kb.ini
.github/workflows/test_docker.yml
.github/workflows/test_tox.yml
config/appveyor/install.ps1
config/appveyor/install.sh
config/appveyor/runtests.sh
config/dpkg/changelog
config/dpkg/clean
config/dpkg/compat
config/dpkg/control
config/dpkg/copyright
config/dpkg/python-winevtrc.install
config/dpkg/python3-winevtrc.install
config/dpkg/rules
config/dpkg/source/format
config/pylint/spelling-private-dict
docs/conf.py
docs/index.rst
docs/requirements.txt
docs/sources/api/modules.rst
docs/sources/api/winevtrc.rst
docs/sources/eventlog-providers/Provider-.NET-Runtime-Optimization-Service.md
docs/sources/eventlog-providers/Provider-.NET-Runtime.md
docs/sources/eventlog-providers/Provider-3ware.md
docs/sources/eventlog-providers/Provider-ACPI.md
docs/sources/eventlog-providers/Provider-ADP80XX.md
docs/sources/eventlog-providers/Provider-AFD.md
docs/sources/eventlog-providers/Provider-AmdK8.md
docs/sources/eventlog-providers/Provider-AmdPPM.md
docs/sources/eventlog-providers/Provider-AppReadiness.md
docs/sources/eventlog-providers/Provider-AppleSSD.md
docs/sources/eventlog-providers/Provider-Application-Addon-Event-Provider.md
docs/sources/eventlog-providers/Provider-Application-Error.md
docs/sources/eventlog-providers/Provider-Application-Hang.md
docs/sources/eventlog-providers/Provider-Application-Management-Group-Policy.md
docs/sources/eventlog-providers/Provider-Application-Management.md
docs/sources/eventlog-providers/Provider-Application-Popup.md
docs/sources/eventlog-providers/Provider-Application.md
docs/sources/eventlog-providers/Provider-AsyncMac.md
docs/sources/eventlog-providers/Provider-AutoEnrollment.md
docs/sources/eventlog-providers/Provider-BTHPORT.md
docs/sources/eventlog-providers/Provider-BTHUSB.md
winevtrc.egg-info/PKG-INFO
winevtrc.egg-info/SOURCES.txt
winevtrc.egg-info/dependency_links.txt
winevtrc.egg-info/requires.txt
winevtrc.egg-info/top_level.txt