Metadata-Version: 2.1
Name: winevtrc
Version: 20220106
Summary: Windows Event Log resources (winevtrc)
Home-page: https://github.com/libyal/winevt-kb
Maintainer: Joachim Metz
Maintainer-email: joachim.metz@gmail.com
License: Apache License, Version 2.0
Platform: UNKNOWN
Classifier: 
Classifier: Environment :: Console
Classifier: Operating System :: OS Independent
Classifier: Programming Language :: Python
License-File: LICENSE
